{
  "listings": [
    {
      "date": "2024-03-14",
      "time": "09:20",
      "address": "2 Rossie Steadings",
      "suburb": "Perth",
      "postcode": "PH20GA",
      "kitchenware": "[k1], [k2],[k3]",
      "electricals": "[e1], [e2],[e3],[e5],[e6]",
      "furniture": "[f1], [f2],[f3],[f4]",
      "otherItems": "",
      "id": 2,
      "dateUpdated": "2024-03-07",
      "timeUpdated": "00:56"
    },
    {
      "date": "2024-03-08",
      "time": "00:27",
      "address": "2 Rossie Steadings",
      "suburb": "Perth",
      "postcode": "PH20GA",
      "kitchenware": "ABC",
      "furniture": "",
      "electricals": "EXAMPLE ELECTRICALS",
      "otherItems": "",
      "dateUpdated": "",
      "timeUpdated": "",
      "id": 5
    },
    {
      "date": "2024-03-16",
      "time": "23:55",
      "address": "139c Railton Road",
      "suburb": "London",
      "postcode": "SE240LT",
      "kitchenware": "ABC",
      "furniture": "Sofa",
      "electricals": "",
      "otherItems": "",
      "dateUpdated": "",
      "timeUpdated": "",
      "id": 3
    },
    {
      "date": "2024-03-09",
      "time": "07:10",
      "address": "115 DENISON STREET",
      "suburb": "BONDI JUNCTION",
      "postcode": "2022",
      "kitchenware": "Plates",
      "furniture": "",
      "electricals": "Hoover",
      "otherItems": "",
      "dateUpdated": "",
      "timeUpdated": "",
      "id": 6
    },
    {
      "date": "2024-03-23",
      "time": "07:11",
      "address": "Unit 9, 16 Military Road",
      "suburb": "North Bondi",
      "postcode": "2026",
      "kitchenware": "Mugs",
      "furniture": "",
      "electricals": "Blender",
      "otherItems": "",
      "dateUpdated": "",
      "timeUpdated": "",
      "id": 7
    },
    {
      "date": "2024-03-15",
      "time": "07:32",
      "address": "139c Railton Road",
      "suburb": "London",
      "postcode": "SE240LT",
      "kitchenware": "Mugs",
      "furniture": "",
      "electricals": "",
      "otherItems": "",
      "dateUpdated": "",
      "timeUpdated": "",
      "id": 8
    },
    {
      "date": "2024-03-15",
      "time": "07:33",
      "address": "Unit 9, 16 Military Road",
      "suburb": "Sydney",
      "postcode": "2026",
      "kitchenware": "",
      "furniture": "Sofabed",
      "electricals": "",
      "otherItems": "SSS",
      "dateUpdated": "",
      "timeUpdated": "",
      "id": 9
    },
    {
      "date": "2024-03-08",
      "time": "13:31",
      "address": "2 Rossie Steadings",
      "suburb": "Perth",
      "postcode": "PH20GA",
      "kitchenware": "Wine glasses",
      "furniture": "",
      "electricals": "Blender",
      "otherItems": "",
      "dateUpdated": "",
      "timeUpdated": "",
      "id": 10
    },
    {
      "date": "2024-03-24",
      "time": "01:01",
      "address": "115 DENISON STREET",
      "suburb": "BONDI JUNCTION",
      "postcode": "2022",
      "kitchenware": "",
      "furniture": "Sofa",
      "electricals": "",
      "otherItems": "AAA, BBB, CCC",
      "dateUpdated": "",
      "timeUpdated": "",
      "id": 11
    },
    {
      "date": "2024-03-16",
      "time": "12:24",
      "address": "Unit 9, 16 Military Road",
      "suburb": "Sydney",
      "postcode": "2026",
      "kitchenware": "",
      "furniture": "",
      "electricals": "[e1], [e2],[e3],[e5],[e6]",
      "otherItems": "Other 1, other 2",
      "dateUpdated": "",
      "timeUpdated": "",
      "other": "",
      "id": 12
    }
  ]
}